notify/__init__.py
notify/notification.py
notify/linux/__init__.py
notify/linux/notify.py
notify/win32/__init__.py
notify/win32/notify.py
notify_send-1.1.1.dist-info/LICENSE
notify_send-1.1.1.dist-info/METADATA
notify_send-1.1.1.dist-info/WHEEL
notify_send-1.1.1.dist-info/top_level.txt
notify_send-1.1.1.dist-info/RECORD
