Metadata-Version: 2.1
Name: notify-send
Version: 1.1.1
Summary: notify-send notify.
Author: Andre P. Santos
Author-email: andreztz@gmail.com
License: MIT
Project-URL: Source, https://github.com/andreztz/notify-send/
Project-URL: Documentation, https://andreztz.github.io/notify-send/
Keywords: alert inform informer notify notify-send
Platform: Linux
Platform: Windows
Classifier: Programming Language :: Python :: 3
Classifier: Intended Audience :: Developers
Requires-Python: >=3.6
License-File: LICENSE
Requires-Dist: pycairo >=1.18.1 ; sys_platform == "linux"
Requires-Dist: PyGObject >=3.34.0 ; sys_platform == "linux"
Requires-Dist: pypiwin32 ==223 ; sys_platform == "win32"
Requires-Dist: pywin32 ==302 ; sys_platform == "win32"
Provides-Extra: build
Requires-Dist: build ; extra == 'build'
Requires-Dist: twine ; extra == 'build'
Provides-Extra: dev
Requires-Dist: pytest ; extra == 'dev'
Requires-Dist: flake8 ; extra == 'dev'
